{
    "text": " Okay, then now recording is in progress. If you are fine with being recorded, let me know please. Okay, perfect. Then we are here to talk about your favorite spots to exercise in Nuremberg. Can you start off by telling me your favorite spot to exercise? There are many opportunities in Nuremberg. How many are there? Okay, can you give me a short overview of all three? Okay, and do you do anything else exercise wise in Nuremberg? One last longer statement. Okay, I also let me interrupt you so we can see how that looks. But what is squashing? Okay, and this really exhausting, right? I've seen this before. Okay, good. I think we have enough. Thank you very much. Any last word? Amazing. Okay, I will stop the recording. Yes. Thank you.",
    "segments": [
        {
            "id": 0,
            "seek": 0,
            "start": 0.0,
            "end": 10.0,
            "text": " Okay, then now recording is in progress. If you are fine with being recorded, let me know please.",
            "tokens": [
                50363,
                16805,
                11,
                788,
                783,
                8296,
                318,
                287,
                4371,
                13,
                1002,
                345,
                389,
                3734,
                351,
                852,
                6264,
                11,
                1309,
                502,
                760,
                3387,
                13,
                50863
            ],
            "temperature": 0.0,
            "avg_logprob": -0.2239443158346509,
            "compression_ratio": 1.5240963855421688,
            "no_speech_prob": 0.005814061500132084
        },
        {
            "id": 1,
            "seek": 0,
            "start": 10.0,
            "end": 18.0,
            "text": " Okay, perfect. Then we are here to talk about your favorite spots to exercise in Nuremberg.",
            "tokens": [
                50863,
                16805,
                11,
                2818,
                13,
                3244,
                356,
                389,
                994,
                284,
                1561,
                546,
                534,
                4004,
                10222,
                284,
                5517,
                287,
                399,
                495,
                47369,
                13,
                51263
            ],
            "temperature": 0.0,
            "avg_logprob": -0.2239443158346509,
            "compression_ratio": 1.5240963855421688,
            "no_speech_prob": 0.005814061500132084
        },
        {
            "id": 2,
            "seek": 0,
            "start": 18.0,
            "end": 23.0,
            "text": " Can you start off by telling me your favorite spot to exercise?",
            "tokens": [
                51263,
                1680,
                345,
                923,
                572,
                416,
                5149,
                502,
                534,
                4004,
                4136,
                284,
                5517,
                30,
                51513
            ],
            "temperature": 0.0,
            "avg_logprob": -0.2239443158346509,
            "compression_ratio": 1.5240963855421688,
            "no_speech_prob": 0.005814061500132084
        },
        {
            "id": 3,
            "seek": 3000,
            "start": 30.0,
            "end": 36.0,
            "text": " There are many opportunities in Nuremberg. How many are there?",
            "tokens": [
                50363,
                1318,
                389,
                867,
                6443,
                287,
                399,
                495,
                47369,
                13,
                1374,
                867,
                389,
                612,
                30,
                50663
            ],
            "temperature": 0.0,
            "avg_logprob": -0.1792144626379013,
            "compression_ratio": 1.1274509803921569,
            "no_speech_prob": 0.013880598358809948
        },
        {
            "id": 4,
            "seek": 3000,
            "start": 46.0,
            "end": 51.0,
            "text": " Okay, can you give me a short overview of all three?",
            "tokens": [
                51163,
                16805,
                11,
                460,
                345,
                1577,
                502,
                257,
                1790,
                16700,
                286,
                477,
                1115,
                30,
                51413
            ],
            "temperature": 0.0,
            "avg_logprob": -0.1792144626379013,
            "compression_ratio": 1.1274509803921569,
            "no_speech_prob": 0.013880598358809948
        },
        {
            "id": 5,
            "seek": 6000,
            "start": 60.0,
            "end": 88.0,
            "text": " Okay, and do you do anything else exercise wise in Nuremberg?",
            "tokens": [
                50363,
                16805,
                11,
                290,
                466,
                345,
                466,
                1997,
                2073,
                5517,
                10787,
                287,
                399,
                495,
                47369,
                30,
                51763
            ],
            "temperature": 0.0,
            "avg_logprob": -0.2876615524291992,
            "compression_ratio": 0.9682539682539683,
            "no_speech_prob": 0.5041998624801636
        },
        {
            "id": 6,
            "seek": 8800,
            "start": 88.0,
            "end": 91.0,
            "text": " One last longer statement.",
            "tokens": [
                50363,
                1881,
                938,
                2392,
                2643,
                13,
                50513
            ],
            "temperature": 0.0,
            "avg_logprob": -0.24180662631988525,
            "compression_ratio": 1.13,
            "no_speech_prob": 0.3074960708618164
        },
        {
            "id": 7,
            "seek": 8800,
            "start": 99.0,
            "end": 104.0,
            "text": " Okay, I also let me interrupt you so we can see how that looks. But what is squashing?",
            "tokens": [
                50913,
                16805,
                11,
                314,
                635,
                1309,
                502,
                11313,
                345,
                523,
                356,
                460,
                766,
                703,
                326,
                3073,
                13,
                887,
                644,
                318,
                2809,
                2140,
                30,
                51163
            ],
            "temperature": 0.0,
            "avg_logprob": -0.24180662631988525,
            "compression_ratio": 1.13,
            "no_speech_prob": 0.3074960708618164
        },
        {
            "id": 8,
            "seek": 11800,
            "start": 118.0,
            "end": 133.0,
            "text": " Okay, and this really exhausting, right? I've seen this before.",
            "tokens": [
                50363,
                16805,
                11,
                290,
                428,
                1107,
                39663,
                11,
                826,
                30,
                314,
                1053,
                1775,
                428,
                878,
                13,
                51113
            ],
            "temperature": 0.0,
            "avg_logprob": -0.2504158020019531,
            "compression_ratio": 1.1842105263157894,
            "no_speech_prob": 0.022798335179686546
        },
        {
            "id": 9,
            "seek": 11800,
            "start": 133.0,
            "end": 142.0,
            "text": " Okay, good. I think we have enough. Thank you very much. Any last word?",
            "tokens": [
                51113,
                16805,
                11,
                922,
                13,
                314,
                892,
                356,
                423,
                1576,
                13,
                6952,
                345,
                845,
                881,
                13,
                4377,
                938,
                1573,
                30,
                51563
            ],
            "temperature": 0.0,
            "avg_logprob": -0.2504158020019531,
            "compression_ratio": 1.1842105263157894,
            "no_speech_prob": 0.022798335179686546
        },
        {
            "id": 10,
            "seek": 14200,
            "start": 142.0,
            "end": 147.0,
            "text": " Amazing. Okay, I will stop the recording. Yes. Thank you.",
            "tokens": [
                50413,
                23181,
                13,
                16805,
                11,
                314,
                481,
                2245,
                262,
                8296,
                13,
                3363,
                13,
                6952,
                345,
                13,
                50613
            ],
            "temperature": 0.0,
            "avg_logprob": -0.2789602014753554,
            "compression_ratio": 0.9193548387096774,
            "no_speech_prob": 0.16795536875724792
        }
    ],
    "language": "en"
}